lamdb/__init__.py
lamdb/__main__.py
lamdb/_config.py
lamdb/cffi.py
lamdb/cpython.cpython-36m-darwin.so
lamdb/tool.py
lamdb-1.2.1.dist-info/LICENSE
lamdb-1.2.1.dist-info/METADATA
lamdb-1.2.1.dist-info/WHEEL
lamdb-1.2.1.dist-info/top_level.txt
lamdb-1.2.1.dist-info/RECORD
